{"cameraMode":{"drawMode":0,"name":"Shaded","section":"Shading Mode"},"sceneLighting":true,"audioPlay":false,"sceneViewState":{"m_AlwaysRefresh":true,"showFog":true,"showSkybox":true,"showFlares":true,"showImageEffects":true,"showParticleSystems":true,"showVisualEffectGraphs":true,"m_FxEnabled":true},"in2DMode":false,"pivot":{"x":-3.1803603172302248,"y":-8.13805103302002,"z":52.64580154418945},"rotation":{"x":-0.1036180779337883,"y":0.00531764468178153,"z":0.002505877986550331,"w":-0.9952720403671265},"size":27.56963348388672,"orthographic":false}